odoo/addons/contract_invoice_auto_validate/README.rst
odoo/addons/contract_invoice_auto_validate/__init__.py
odoo/addons/contract_invoice_auto_validate/__manifest__.py
odoo/addons/contract_invoice_auto_validate/i18n/contract_invoice_auto_validate.pot
odoo/addons/contract_invoice_auto_validate/i18n/fr.po
odoo/addons/contract_invoice_auto_validate/i18n/it.po
odoo/addons/contract_invoice_auto_validate/i18n/sv.po
odoo/addons/contract_invoice_auto_validate/migrations/18.0.1.0.1/post-migrate.py
odoo/addons/contract_invoice_auto_validate/models/__init__.py
odoo/addons/contract_invoice_auto_validate/models/contract_contract.py
odoo/addons/contract_invoice_auto_validate/models/res_company.py
odoo/addons/contract_invoice_auto_validate/models/res_config_settings.py
odoo/addons/contract_invoice_auto_validate/readme/CONTRIBUTORS.md
odoo/addons/contract_invoice_auto_validate/readme/DESCRIPTION.md
odoo/addons/contract_invoice_auto_validate/readme/USAGE.md
odoo/addons/contract_invoice_auto_validate/static/description/icon.png
odoo/addons/contract_invoice_auto_validate/static/description/index.html
odoo/addons/contract_invoice_auto_validate/tests/__init__.py
odoo/addons/contract_invoice_auto_validate/tests/test_contract_invoice_auto_validate.py
odoo/addons/contract_invoice_auto_validate/views/res_config_settings.xml
odoo_addon_contract_invoice_auto_validate-18.0.1.0.1.8.dist-info/METADATA
odoo_addon_contract_invoice_auto_validate-18.0.1.0.1.8.dist-info/WHEEL
odoo_addon_contract_invoice_auto_validate-18.0.1.0.1.8.dist-info/top_level.txt
odoo_addon_contract_invoice_auto_validate-18.0.1.0.1.8.dist-info/RECORD
