Metadata-Version: 2.1
Name: odoo-addon-contract_invoice_auto_validate
Version: 18.0.1.0.1.8
Requires-Python: >=3.10
Requires-Dist: odoo-addon-contract==18.0.*
Requires-Dist: odoo==18.0.*
Summary: This addon auto-validate invoices after its creation from a contract
Home-page: https://github.com/OCA/contract
License: AGPL-3
Author: ACSONE SA/NV,Odoo Community Association (OCA)
Author-email: support@odoo-community.org
Classifier: Programming Language :: Python
Classifier: Framework :: Odoo
Classifier: Framework :: Odoo :: 18.0
Classifier: License :: OSI Approved :: GNU Affero General Public License v3
